Metadata-Version: 2.1
Name: magiepy
Version: 0.0.1.dev0
Summary: Python utilities for the Magnetometer Network of Ireland (MagIE)
License: Copyright (c) 2024, DIAS Solar
Project-URL: repository, https://github.com/TCDSolar/MagIEpy
Requires-Python: >=3.10
Provides-Extra: test
Requires-Dist: pytest; extra == "test"
Requires-Dist: pytest-doctestplus; extra == "test"
Requires-Dist: pytest-cov; extra == "test"
Provides-Extra: docs
Requires-Dist: sphinx; extra == "docs"
Requires-Dist: sphinx-automodapi; extra == "docs"
